synch_fifo.v
module synch_fifo(
    input clk,
    input rst,
    input wr_en,
    input rd_en,
    input [7:0] data_in,
    output full,
    output empty,
    output reg [7:0] data_out
);

reg [7:0] memory [0:7];
reg [3:0] wr_ptr, rd_ptr;   // extra MSB
integer i;

always @(posedge clk or negedge rst) begin
    if (!rst) begin
        for (i = 0; i < 8; i = i + 1)
            memory[i] <= 8'd0;

        wr_ptr   <= 4'd0;
        rd_ptr   <= 4'd0;
        data_out <= 8'd0;
    end
    else begin
        // WRITE
        if (wr_en) begin
            memory[wr_ptr[2:0]] <= data_in;
            wr_ptr <= wr_ptr + 1'b1;
        end

        // READ
        if (rd_en) begin
            data_out <= memory[rd_ptr[2:0]];
            rd_ptr <= rd_ptr + 1'b1;
        end
    end
end

assign empty = (wr_ptr == rd_ptr);

assign full  = (wr_ptr[3] != rd_ptr[3]) &&
               (wr_ptr[2:0] == rd_ptr[2:0]);

endmodule

tb.v
`include "synch_fifo.v"
`timescale 1ns/1ps

module tb_synch_fifo;

    // DUT signals
    reg clk;
    reg rst;
    reg wr_en;
    reg rd_en;
    reg [7:0] data_in;

    wire full;
    wire empty;
    wire [7:0] data_out;

    // Instantiate DUT
    synch_fifo dut (
        .clk(clk),
        .rst(rst),
        .wr_en(wr_en),
        .rd_en(rd_en),
        .data_in(data_in),
        .full(full),
        .empty(empty),
        .data_out(data_out)
    );

    // -------------------------
    // Clock generation (10 ns)
    // -------------------------
    always #5 clk = ~clk;

    // -------------------------
    // Test sequence
    // -------------------------
    initial begin
        // Init
        clk     = 0;
        rst     = 0;
        wr_en   = 0;
        rd_en   = 0;
        data_in= 8'd0;

        // Apply reset
        #10;
        rst = 1;

        // -------------------------
        // WRITE 5 values
        // -------------------------
        repeat (5) begin
            @(posedge clk);
            wr_en   = 1;
            data_in = $random;
        end

        @(posedge clk);
        wr_en = 0;


        // -------------------------
        // READ 3 values
        // -------------------------
        repeat (5) begin
            @(posedge clk);
            rd_en = 1;
        end

        @(posedge clk);
        rd_en = 0;

        // Finish simulation
        #40;
        $finish;
    end

    initial begin
        $dumpfile("fifo_tb.vcd");
        $dumpvars(0,tb_synch_fifo);
    end

endmodule

fifo_tb.vcd
$date
	Wed Jan 07 20:50:58 2026
$end
$version
	Icarus Verilog
$end
$timescale
	1ps
$end
$scope module tb_synch_fifo $end
$var wire 1 ! full $end
$var wire 1 " empty $end
$var wire 8 # data_out [7:0] $end
$var reg 1 $ clk $end
$var reg 8 % data_in [7:0] $end
$var reg 1 & rd_en $end
$var reg 1 ' rst $end
$var reg 1 ( wr_en $end
$scope module dut $end
$var wire 1 $ clk $end
$var wire 8 ) data_in [7:0] $end
$var wire 1 ! full $end
$var wire 1 & rd_en $end
$var wire 1 ' rst $end
$var wire 1 ( wr_en $end
$var wire 1 " empty $end
$var reg 8 * data_out [7:0] $end
$var reg 4 + rd_ptr [3:0] $end
$var reg 4 , wr_ptr [3:0] $end
$var integer 32 - i [31:0] $end
$upscope $end
$upscope $end
$enddefinitions $end
#0
$dumpvars
b1000 -
b0 ,
b0 +
b0 *
b0 )
0(
0'
0&
b0 %
0$
b0 #
1"
0!
$end
#5000
b1000 -
1$
#10000
0$
1'
#15000
0"
b1 ,
b100100 %
b100100 )
1(
1$
#20000
0$
#25000
b10 ,
b10000001 %
b10000001 )
1$
#30000
0$
#35000
b11 ,
b1001 %
b1001 )
1$
#40000
0$
#45000
b100 ,
b1100011 %
b1100011 )
1$
#50000
0$
#55000
b101 ,
b1101 %
b1101 )
1$
#60000
0$
#65000
0(
1$
#70000
0$
#75000
b1 +
b100100 #
b100100 *
1&
1$
#80000
0$
#85000
b10 +
b10000001 #
b10000001 *
1$
#90000
0$
#95000
b11 +
b1001 #
b1001 *
1$
#100000
0$
#105000
b100 +
b1100011 #
b1100011 *
1$
#110000
0$
#115000
1"
b101 +
b1101 #
b1101 *
1$
#120000
0$
#125000
0&
1$
